blackfox_extras/__init__.py
blackfox_extras/calculate_metrics.py
blackfox_extras/data_extras.py
blackfox_extras/encode_data_set.py
blackfox_extras/encode_variable.py
blackfox_extras/input_extras.py
blackfox_extras/load_models.py
blackfox_extras/rnn_extras.py
blackfox_extras/scaler_extras.py
blackfox_extras/series_extras.py
blackfox_extras-1.3.5.dist-info/METADATA
blackfox_extras-1.3.5.dist-info/WHEEL
blackfox_extras-1.3.5.dist-info/top_level.txt
blackfox_extras-1.3.5.dist-info/RECORD
