Metadata-Version: 2.1
Name: blackfox-extras
Version: 1.3.5
Summary: BlackFox Extras
Home-page: https://github.com/vodena/BlackFoxPythonExtras
Author: Tomislav Mrdja
Author-email: 
Keywords: BlackFox
Requires-Dist: blackfox (>=6.1.0)
Requires-Dist: numpy (>=1.19.1)
Requires-Dist: scikit-learn (>=1.0.0)
Requires-Dist: pandas (>=0.25.3)
Requires-Dist: category-encoders (>=2.2.2)
Requires-Dist: tensorflow (>=2.6.1)
Requires-Dist: xgboost (==1.5.0)
